phase_puml/__init__.py
phase_puml-0.0.1.dist-info/LICENSE
phase_puml-0.0.1.dist-info/METADATA
phase_puml-0.0.1.dist-info/WHEEL
phase_puml-0.0.1.dist-info/top_level.txt
phase_puml-0.0.1.dist-info/RECORD
